Flask_RESTBuilder-0.1.0.data/data/templates/project_tpl/.gitignore-tpl
Flask_RESTBuilder-0.1.0.data/data/templates/project_tpl/CHANGES.rst-tpl
Flask_RESTBuilder-0.1.0.data/data/templates/project_tpl/README.rst-tpl
Flask_RESTBuilder-0.1.0.data/data/templates/project_tpl/src_tpl/project_name/__init__.py-tpl
Flask_RESTBuilder-0.1.0.data/data/templates/project_tpl/src_tpl/project_name/config.py-tpl
Flask_RESTBuilder-0.1.0.data/data/templates/project_tpl/src_tpl/project_name/manage.py-tpl
Flask_RESTBuilder-0.1.0.data/data/templates/project_tpl/src_tpl/project_name/app_tpl/__init__.py-tpl
Flask_RESTBuilder-0.1.0.data/data/templates/project_tpl/src_tpl/project_name/app_tpl/api_tpl/__init__.py-tpl
Flask_RESTBuilder-0.1.0.data/data/templates/project_tpl/src_tpl/project_name/app_tpl/api_tpl/api.py-tpl
Flask_RESTBuilder-0.1.0.data/data/templates/project_tpl/src_tpl/project_name/app_tpl/app_name/__init__.py-tpl
Flask_RESTBuilder-0.1.0.data/data/templates/project_tpl/src_tpl/project_name/app_tpl/app_name/models.py-tpl
Flask_RESTBuilder-0.1.0.data/data/templates/project_tpl/src_tpl/project_name/app_tpl/app_name/routes.py-tpl
Flask_RESTBuilder-0.1.0.data/data/templates/project_tpl/src_tpl/project_name/extension_tpl/__init__.py-tpl
Flask_RESTBuilder-0.1.0.data/data/templates/project_tpl/src_tpl/project_name/extension_tpl/mysql.py-tpl
flask_restbuilder/__init__.py
flask_restbuilder/cli.py
flask_restbuilder/decorators.py
flask_restbuilder/exceptions.py
flask_restbuilder/views.py
flask_restbuilder/templates/project_tpl/.gitignore-tpl
flask_restbuilder/templates/project_tpl/CHANGES.rst-tpl
flask_restbuilder/templates/project_tpl/README.rst-tpl
flask_restbuilder/templates/project_tpl/src_tpl/project_name/__init__.py-tpl
flask_restbuilder/templates/project_tpl/src_tpl/project_name/config.py-tpl
flask_restbuilder/templates/project_tpl/src_tpl/project_name/manage.py-tpl
flask_restbuilder/templates/project_tpl/src_tpl/project_name/app_tpl/__init__.py-tpl
Flask_RESTBuilder-0.1.0.dist-info/AUTHORS.rst
Flask_RESTBuilder-0.1.0.dist-info/LICENSE.rst
Flask_RESTBuilder-0.1.0.dist-info/METADATA
Flask_RESTBuilder-0.1.0.dist-info/WHEEL
Flask_RESTBuilder-0.1.0.dist-info/entry_points.txt
Flask_RESTBuilder-0.1.0.dist-info/top_level.txt
Flask_RESTBuilder-0.1.0.dist-info/RECORD
