Metadata-Version: 2.1
Name: Flask-RESTBuilder
Version: 0.1.0
Summary: A Flask-based framework for easy REST API projects building.
Home-page: https://github.com/TnTomato/flask_restbuilder
Author: TnTomato
Author-email: 474093103@qq.com
Maintainer: TnTomato
License: BSD-3-Clause
Project-URL: Code, https://github.com/TnTomato/flask_restbuilder
Platform: UNKNOWN
Classifier: Development Status :: 2 - Pre-Alpha
Classifier: Intended Audience :: Developers
Classifier: License :: OSI Approved :: BSD License
Classifier: Framework :: Flask
Classifier: Natural Language :: English
Classifier: Programming Language :: Python
Classifier: Programming Language :: Python :: 3 :: Only
Classifier: Programming Language :: Python :: 3.8
Requires-Python: >=3.8
Requires-Dist: aniso8601 (>=8.0.0)
Requires-Dist: attrs (>=20.1.0)
Requires-Dist: click (>=7.1.2)
Requires-Dist: flasgger (>=0.9.5)
Requires-Dist: Flask (>=1.1.2)
Requires-Dist: Flask-RESTful (>=0.3.8)
Requires-Dist: Flask-Script (>=2.0.6)
Requires-Dist: Flask-SQLAlchemy (>=2.4.4)
Requires-Dist: itsdangerous (>=1.1.0)
Requires-Dist: Jinja2 (>=2.11.2)
Requires-Dist: jsonschema (>=3.2.0)
Requires-Dist: MarkupSafe (>=1.1.1)
Requires-Dist: mistune (>=0.8.4)
Requires-Dist: pymongo (>=3.11.0)
Requires-Dist: pyrsistent (>=0.16.0)
Requires-Dist: pytz (>=2020.1)
Requires-Dist: PyYAML (>=5.3.1)
Requires-Dist: six (>=1.15.0)
Requires-Dist: SQLAlchemy (>=1.3.19)
Requires-Dist: Werkzeug (>=1.0.1)
